snandi.pypy36-pp73-win32.pyd
ndizta/__init__.py
ndizta/core.py
ndizta-0.0.2.dist-info/LICENSE
ndizta-0.0.2.dist-info/METADATA
ndizta-0.0.2.dist-info/WHEEL
ndizta-0.0.2.dist-info/top_level.txt
ndizta-0.0.2.dist-info/RECORD
